ckanext_matolabtheme-1.0.6-py3.13-nspkg.pth
ckanext/matolabtheme/__init__.py
ckanext/matolabtheme/action.py
ckanext/matolabtheme/auth.py
ckanext/matolabtheme/helpers.py
ckanext/matolabtheme/plugin.py
ckanext/matolabtheme/views.py
ckanext/matolabtheme/assets/dark.css
ckanext/matolabtheme/assets/index.js
ckanext/matolabtheme/assets/script.js
ckanext/matolabtheme/assets/style.css
ckanext/matolabtheme/assets/webassets.yml
ckanext/matolabtheme/i18n/de/LC_MESSAGES/ckanext-matolabtheme.mo
ckanext/matolabtheme/public/static/Logo.svg
ckanext/matolabtheme/public/static/banner_bottom.png
ckanext/matolabtheme/public/static/banner_top.png
ckanext/matolabtheme/public/static/favicon.png
ckanext/matolabtheme/public/static/voronoi_bg.png
ckanext/matolabtheme/templates/base.html
ckanext/matolabtheme/templates/footer.html
ckanext/matolabtheme/templates/header.html
ckanext/matolabtheme/templates/page.html
ckanext/matolabtheme/templates/admin/config.html
ckanext/matolabtheme/templates/home/index.html
ckanext/matolabtheme/templates/home/snippets/featured_group.html
ckanext/matolabtheme/templates/home/snippets/featured_organization.html
ckanext/matolabtheme/templates/home/snippets/promoted.html
ckanext/matolabtheme/templates/matolabtheme/dataprivacy.html
ckanext/matolabtheme/templates/matolabtheme/theme_config.html
ckanext/matolabtheme/templates/user/login.html
ckanext/matolabtheme/tests/__init__.py
ckanext/matolabtheme/tests/test_plugin.py
ckanext_matolabtheme-1.0.6.dist-info/licenses/LICENSE
ckanext_matolabtheme-1.0.6.dist-info/METADATA
ckanext_matolabtheme-1.0.6.dist-info/WHEEL
ckanext_matolabtheme-1.0.6.dist-info/entry_points.txt
ckanext_matolabtheme-1.0.6.dist-info/namespace_packages.txt
ckanext_matolabtheme-1.0.6.dist-info/top_level.txt
ckanext_matolabtheme-1.0.6.dist-info/RECORD
