Metadata-Version: 2.4
Name: ckanext-matolabtheme
Version: 1.0.6
Summary: CKAN theme of the Mat-O-Lab Project, changes landing Page and add alternative Data Privacy Act in English and German.
Home-page: https://github.com/Mat-O-Lab/ckanext-matolabtheme
Author: Thomas Hanke
Author-email: thomas.hanke@iwm.fraunhofer.de
License: AGPL
Keywords: CKAN Theme
Classifier: Development Status :: 4 - Beta
Classifier: License :: OSI Approved :: GNU Affero General Public License v3 or later (AGPLv3+)
Classifier: Programming Language :: Python :: 3.7
Classifier: Programming Language :: Python :: 3.8
Classifier: Programming Language :: Python :: 3.9
Classifier: Programming Language :: Python :: 3.10
License-File: LICENSE
Requires-Dist: requests>=2.4.2
Requires-Dist: sqlalchemy
Requires-Dist: pytest
Requires-Dist: pytest-ckan
Dynamic: author
Dynamic: author-email
Dynamic: description
Dynamic: description-content-type
Dynamic: home-page
Dynamic: license
Dynamic: license-file
Dynamic: requires-dist
Dynamic: summary
